zombie_calculator/__init__.py
zombie_calculator/__main__.py
zombie_calculator/asmInject.cp38-win_amd64.pyd
zombie_calculator/config.py
zombie_calculator/seedFinder.cp38-win_amd64.pyd
zombie_calculator/zombie_calculator.py
zombie_calculator/gui/__init__.py
zombie_calculator/gui/introduction.py
zombie_calculator/gui/introduction.ui
zombie_calculator/gui/main.py
zombie_calculator/gui/mode1.py
zombie_calculator/gui/mode1.ui
zombie_calculator/gui/mode2.py
zombie_calculator/gui/mode2.ui
zombie_calculator/gui/modify.py
zombie_calculator/gui/modify.ui
zombie_calculator/gui/msg.py
zombie_calculator/gui/msg.ui
zombie_calculator/pack_resources/icon.ico
zombie_calculator/pack_resources/help/check.png
zombie_calculator/pack_resources/help/check_2.png
zombie_calculator/pack_resources/help/help.html
zombie_calculator/pack_resources/help/help.md
zombie_calculator/pack_resources/help/mode1.png
zombie_calculator/pack_resources/help/mode1Result.png
zombie_calculator/pack_resources/help/mode2_1.png
zombie_calculator/pack_resources/help/mode2_1Result.png
zombie_calculator/pack_resources/help/mode2_2.1.png
zombie_calculator/pack_resources/help/mode2_2.2.png
zombie_calculator/pack_resources/help/mode2_2Result.png
zombie_calculator/pack_resources/help/modify.png
zombie_calculator/pack_resources/help/modify_2.png
zombie_calculator/pack_resources/help/users.png
zombie_calculator/pack_resources/language/zh_CN.qm
zombie_calculator/pack_resources/qt_material/material.css.template
zombie_calculator-0.0.4.3.dist-info/METADATA
zombie_calculator-0.0.4.3.dist-info/WHEEL
zombie_calculator-0.0.4.3.dist-info/entry_points.txt
zombie_calculator-0.0.4.3.dist-info/top_level.txt
zombie_calculator-0.0.4.3.dist-info/RECORD
