Metadata-Version: 2.1
Name: zombie-calculator
Version: 0.0.4.3
Summary: A program used to calculate specific pvz spawn seed.
Home-page: https://github.com/Kndy666/zombie_calculator
Author: kndy666
Author-email: kndy_666@163.com
License: GNU Lesser General Public License
Keywords: pvz
Platform: UNKNOWN
Classifier: Development Status :: 5 - Production/Stable
Classifier: Environment :: Win32 (MS Windows)
Classifier: Natural Language :: Chinese (Simplified)
Classifier: Operating System :: Microsoft :: Windows
Classifier: Programming Language :: C++
Classifier: Programming Language :: Python :: 3.8
Classifier: Topic :: Games/Entertainment
Classifier: License :: OSI Approved :: GNU Lesser General Public License v3 (LGPLv3)
Requires-Dist: bidict (>=0.22.0)
Requires-Dist: pathlib (>=1.0.1)
Requires-Dist: PyQt5 (>=5.15.4)
Requires-Dist: qt-material (>=2.12)
Requires-Dist: pyperclip (>=1.8.2)
Provides-Extra: nuitka
Requires-Dist: nuitka (>=1.0.4) ; extra == 'nuitka'
